[
      {
        "id":155983,
        "updateTime":"2014-11-13T13:32:44.555Z",
        "gender":1},
      {
        "id":174778,
        "updateTime":"2014-11-13T05:25:57.418Z",
        "gender":2,
        "pt":"31.271609,120.73913"},
      {
        "id":174776,
        "updateTime":"2014-11-13T05:25:30.192Z",
        "gender":2,
        "pt":"31.271709,120.73913"},
      {
        "id":166158,
        "updateTime":"2014-11-14T03:13:42.661Z",
        "gender":2,
        "pt":"31.271809,120.73913"},
      {
        "id":165049,
        "updateTime":"2014-11-14T02:01:05.04Z",
        "gender":1,
        "pt":"31.271909,120.73913"},
      {
        "id":165724,
        "updateTime":"2014-11-14T02:21:04.026Z",
        "gender":1,
        "pt":"31.272609,120.73913"},
      {
        "id":174781,
        "updateTime":"2014-11-14T02:24:17.824Z",
        "gender":2,
        "pt":"31.273609,120.73913"},
      {
        "id":158506,
        "updateTime":"2014-11-14T03:38:40.792Z",
        "gender":1,
        "pt":"31.274609,120.73913"},
      {
        "id":169352,
        "updateTime":"2014-11-14T05:19:10.707Z",
        "gender":1,
        "pt":"31.275609,120.73913"},
      {
        "id":154681,
        "updateTime":"2014-11-14T07:15:07.074Z",
        "gender":1,
        "pt":"31.276609,120.73913"},
      {
        "id":154620,
        "updateTime":"2014-11-17T06:10:51.316Z",
        "gender":1,
        "pt":"31.277609,120.73913"},
      {
        "id":181070,
        "updateTime":"2014-11-13T02:37:27.215Z",
        "gender":1,
        "pt":"31.2646,120.73368"},
      {
        "id":174774,
        "updateTime":"2014-11-18T09:32:20.146Z",
        "gender":2,
        "pt":"31.278609,120.73913"},
      {
        "id":154621,
        "updateTime":"2014-11-17T06:53:56.914Z",
        "gender":1,
        "pt":"31.279609,120.73913"},
      {
        "id":172272,
        "updateTime":"2014-11-19T01:55:21.271Z",
        "gender":1,
        "pt":"31.261609,120.73913"},
      {
        "id":181601,
        "updateTime":"2014-11-17T06:57:12.08Z",
        "gender":2,
        "pt":"31.251609,120.73913"},
      {
        "id":165844,
        "updateTime":"2014-11-18T07:44:04.087Z",
        "gender":1,
        "pt":"31.241609,120.73913"},
      {
        "id":174780,
        "updateTime":"2014-11-19T02:31:52.354Z",
        "gender":2,
        "pt":"31.231609,120.73913"},
      {
        "id":181373,
        "updateTime":"2014-11-19T01:57:45.331Z",
        "gender":1,
        "pt":"31.221609,120.73913"},
      {
        "id":174341,
        "updateTime":"2014-11-19T03:23:39.102Z",
        "gender":2,
        "pt":"31.211609,120.73913"},
      {
        "id":187111,
        "updateTime":"2014-11-19T05:30:49.782Z",
        "gender":2,
        "pt":"31.201609,120.73913"},
      {
        "id":174346,
        "updateTime":"2014-11-19T03:02:55.145Z",
        "gender":1,
        "pt":"31.371609,120.73913"},
      {
        "id":172910,
        "updateTime":"2014-11-19T03:14:31.951Z",
        "gender":1,
        "pt":"31.471609,120.73913"},
      {
        "id":163429,
        "updateTime":"2014-11-19T03:38:23.862Z",
        "gender":1,
        "pt":"31.571609,120.73913"},
      {
        "id":174773,
        "updateTime":"2014-11-19T05:41:02.398Z",
        "gender":2,
        "pt":"31.671609,120.73913"},
      {
        "id":172407,
        "updateTime":"2014-11-19T05:53:36.789Z",
        "gender":2,
        "pt":"31.771609,120.73913"},
      {
        "id":150775,
        "updateTime":"2014-11-19T03:02:43.043Z",
        "gender":1,
        "pt":"31.871609,120.73913"},
      {
        "id":169117,
        "gender":1,
        "updateTime":"2014-11-19T05:53:37.419Z",
        "pt":"31.971609,120.73913"},
      {
        "id":159958,
        "updateTime":"2014-11-19T05:54:01.661Z",
        "gender":1,
        "pt":"32.271609,120.73913"}]

